EDAPlayground/Half-Adder/Files/design.sv
// Code Verilog Here:
// Data Flow Model

module halfadd1(a, b, sum, carry);
  input a, b;
  output sum, carry;
  
  assign sum = a ^ b;
  assign carry = a & b;
  
endmodule

EDAPlayground/Half-Adder/Files/testbench.sv
// Code your testbench here:

module tb_HALFADD;
  
  reg A, B;
  wire SUM, CARRY;
  
  // note the syntax: connect a to A, b to B, Y to y, etc.
  halfadd1 ha1 (.a(A), .b(B), .sum(SUM), .carry(CARRY)); // instantiation: connect TB to Design

  initial begin
  	A = 1'b0; // Force 1 bit value of 0 to A
    B = 1'b0; // Force 1 bit value of 0 to B
    #40 $finish;
  end
  
  always #2 A = ~A;
  always #4 B = ~B;
  always @(SUM, CARRY)
    
 	// Display time and variable values:
    $display("time = %0t \tINPUT VALUES: \tA = %b \tB = %b \tOutput SUM = %b \tOutput CARRY = %b",$time,A,B,SUM,CARRY); 
  initial begin
    $dumpfile("tb_HALFADD.vcd"); 	// Extract waveforms from test bench to file.
    $dumpvars(0, tb_HALFADD);		// Extract Variable values to file.
  end
endmodule

EDAPlayground/Half-Adder/Files/tb_HALFADD.vcd
$date
	Sat Mar  9 12:24:16 2024
$end

$version
	Synopsys VCS version S-2021.09
$end

$timescale
	1ns
$end

$comment Csum: 1 2eba96036b040f72 $end


$scope module tb_HALFADD $end
$var reg 1 ! A $end
$var reg 1 " B $end
$var wire 1 # SUM $end
$var wire 1 $ CARRY $end

$scope module ha1 $end
$var wire 1 ! a $end
$var wire 1 " b $end
$var wire 1 # sum $end
$var wire 1 $ carry $end
$upscope $end

$upscope $end

$enddefinitions $end

#0
$dumpvars
0!
0"
0#
0$
$end
#2
1!
1#
#4
1"
0#
1$
0!
1#
0$
#6
1!
0#
1$
#8
0"
1#
0$
0!
0#
#10
1!
1#
#12
1"
0#
1$
0!
1#
0$
#14
1!
0#
1$
#16
0"
1#
0$
0!
0#
#18
1!
1#
#20
1"
0#
1$
0!
1#
0$
#22
1!
0#
1$
#24
0"
1#
0$
0!
0#
#26
1!
1#
#28
1"
0#
1$
0!
1#
0$
#30
1!
0#
1$
#32
0"
1#
0$
0!
0#
#34
1!
1#
#36
1"
0#
1$
0!
1#
0$
#38
1!
0#
1$
