EDAPlayground/Practice2/Files/design.sv
// Code your design here

module practice2 (
  input a, b, c, d,
  output q
);
  
  wire aAndBorNotc;
  assign aAndBorNotC = (a & b) | (!c); // Intermediate connection
  
  assign q = !(aAndBorNotC & d);
  
endmodule

EDAPlayground/Practice2/Files/testbench.sv
// Code your testbench here

module tb_practice2;

  // Clock Generation
  localparam CLK_PER = 10; // Clock period in units
  reg clk = 0;
  
  reg A, B, C, D;
  wire Q;

  // Instantiate the module under test
  practice2 p1 (
    .a(A),
    .b(B),
    .c(C),
    .d(D),
    .q(Q)
  );

  always #((CLK_PER) / 2) clk = ~clk;

  initial begin

    A = 0; B = 0; C = 0; D = 0;	    // Initialize inputs
    #20 A = 0; B = 0; C = 0; D = 0;
    #20 A = 0; B = 0; C = 0; D = 1;
    #20 A = 0; B = 0; C = 1; D = 0;
    #20 A = 0; B = 0; C = 1; D = 1;
    #20 A = 0; B = 1; C = 0; D = 0;
    #20 A = 0; B = 1; C = 0; D = 1;
    #20 A = 0; B = 1; C = 1; D = 0;
    #20 A = 0; B = 1; C = 1; D = 1;
    #20 A = 1; B = 0; C = 0; D = 0;
    #20 A = 1; B = 0; C = 0; D = 1;
    #20 A = 1; B = 0; C = 1; D = 0;
    #20 A = 1; B = 0; C = 1; D = 1;
    #20 A = 1; B = 1; C = 0; D = 0;
    #20 A = 1; B = 1; C = 0; D = 1;
    #20 A = 1; B = 1; C = 1; D = 0;
    #20 A = 1; B = 1; C = 1; D = 1;
    #40 $finish;					// Delay before end in time units.

  end

  always @(posedge clk) begin
    
    $display("Time = %0t \tA = %b \tB = %b \tC = %b \tD = %b \tQ = %b", $time, A, B, C, D, Q);

  end
  initial begin
    $dumpfile("tb_practice2.vcd"); 	// Extract waveforms from test bench to file.
    $dumpvars(0, tb_practice2);		// Extract Variable values to file.
  end

endmodule

EDAPlayground/Practice2/Files/tb_practice2.vcd
$date
	Wed Mar 13 15:05:22 2024
$end

$version
	Synopsys VCS version S-2021.09
$end

$timescale
	1ns
$end

$comment Csum: 1 6254327e0735ec16 $end


$scope module tb_practice2 $end
$var reg 1 ! clk $end
$var reg 1 " A $end
$var reg 1 # B $end
$var reg 1 $ C $end
$var reg 1 % D $end
$var wire 1 & Q $end

$scope module p1 $end
$var wire 1 " a $end
$var wire 1 # b $end
$var wire 1 $ c $end
$var wire 1 % d $end
$var wire 1 & q $end
$var wire 1 ' aAndBorNotc $end
$var wire 1 ( aAndBorNotC $end
$upscope $end

$upscope $end

$enddefinitions $end

#0
$dumpvars
0"
0#
0$
0%
1&
0!
x(
z'
$end
1(
#5
1!
#10
0!
#15
1!
#20
0!
#25
1!
#30
0!
#35
1!
#40
1%
0!
0&
#45
1!
#50
0!
#55
1!
#60
1$
0(
0%
0!
1&
#65
1!
#70
0!
#75
1!
#80
1%
0!
#85
1!
#90
0!
#95
1!
#100
1#
1(
0$
0%
0!
#105
1!
#110
0!
#115
1!
#120
1%
0!
0&
#125
1!
#130
0!
#135
1!
#140
1$
0(
0%
0!
1&
#145
1!
#150
0!
#155
1!
#160
1%
0!
#165
1!
#170
0!
#175
1!
#180
1"
1(
0#
0$
0%
0!
#185
1!
#190
0!
#195
1!
#200
1%
0!
0&
#205
1!
#210
0!
#215
1!
#220
1$
0(
0%
0!
1&
#225
1!
#230
0!
#235
1!
#240
1%
0!
#245
1!
#250
0!
#255
1!
#260
1#
1(
0$
0%
0!
#265
1!
#270
0!
#275
1!
#280
1%
0!
0&
#285
1!
#290
0!
#295
1!
#300
1$
0%
0!
1&
#305
1!
#310
0!
#315
1!
#320
1%
0!
0&
