EDAPlayground/AND-OR-2/Files/design.sv
// Code Verilog Here:
// Data Flow Model

module and2(a, b, y, z);
	input a, b;
  	output y, z;
  
  	assign y = a & b; // 2 input AND Gate
  	assign z = a | b; // 2 input OR Gate
  
endmodule

EDAPlayground/AND-OR-2/Files/testbench.sv
// Code your testbench here:

module tb_AND;
  
  reg A, B;
  wire Y, Z;
  
  // note the syntax: connect a to A, b to B, Y to y, etc.
  and2 a1 (.a(A), .b(B), .y(Y), .z(Z)); // instantiation: connect TB to Design

  initial begin
  	A = 1'b0; // Force 1 bit value of 0 to A
    B = 1'b0; // Force 1 bit value of 0 to B
    #45 $finish;
  end
  
  always #6 A = ~A;
  always #3 B = ~B;
  always @(Y, Z)
    
 	// Display time and variable values:
    $display("time = %0t \tINPUT VALUES: \tA = %b \tB = %b \tOutput Y = %b \tOutput Z = %b",$time,A,B,Y,Z); 
  initial begin
    $dumpfile("tb_AND.vcd"); 	// Extract waveforms from test bench to file.
    $dumpvars(0, tb_AND);		// Extract Variable values to file.
  end
endmodule

EDAPlayground/AND-OR-2/Files/tb_AND.vcd
$date
	Fri Mar  8 13:03:34 2024
$end

$version
	Synopsys VCS version S-2021.09
$end

$timescale
	1ns
$end

$comment Csum: 1 52424f5928ae1287 $end


$scope module tb_AND $end
$var reg 1 ! A $end
$var reg 1 " B $end
$var wire 1 # Y $end
$var wire 1 $ Z $end

$scope module a1 $end
$var wire 1 ! a $end
$var wire 1 " b $end
$var wire 1 # y $end
$var wire 1 $ z $end
$upscope $end

$upscope $end

$enddefinitions $end

#0
$dumpvars
0!
0"
0#
0$
$end
#3
1"
1$
#6
1!
1#
0"
0#
#9
1"
1#
#12
0!
0#
0"
0$
#15
1"
1$
#18
1!
1#
0"
0#
#21
1"
1#
#24
0!
0#
0"
0$
#27
1"
1$
#30
1!
1#
0"
0#
#33
1"
1#
#36
0!
0#
0"
0$
#39
1"
1$
#42
1!
1#
0"
0#
