EDAPlayground/Full-Adder1/Files/design.sv
// Code Verilog Here:
// Data Flow Model

module fulladd1 (
    input A,
    input B,
    input CIN,
    output SUM,
    output COUT 
);

    assign SUM = A ^ B ^ CIN;
  	assign COUT = (A & B) | (CIN & (A ^ B));

endmodule

EDAPlayground/Full-Adder1/Files/testbench.sv
// Code your testbench here:

module tb_FULLADD_1;

    localparam CLK_PER = 10; // Clock period
    reg clk = 0; 			 // Initialize Clock signal to Zero
  	reg X, Y;    			 // Inputs
    reg CINtest;
    
    wire COUTtest;			 // Outputs
  	wire SUMtest;

  	// Clock Generation
    always #((CLK_PER) / 2) clk = ~clk;

    // Connect Test Bench to the Module Under Test
  	fulladd1 fa1 (
      .A(X),
      .B(Y), 
      .CIN(CINtest),
      .COUT(COUTtest),
      .SUM(SUMtest)
    );

    // Test Routine Start:
    initial begin
    	X = 1'b0; // Change values as needed
        Y = 1'b0;
        CINtest = 0;

        // Apply stimulus
        #10 X = 1'b0; Y = 1'b0; CINtest = 0;
      	#10 X = 1'b0; Y = 1'b0; CINtest = 1;
      	#10 X = 1'b0; Y = 1'b1; CINtest = 0;
        #10 X = 1'b0; Y = 1'b1; CINtest = 1;
      	#10 X = 1'b1; Y = 1'b0; CINtest = 0;
      	#10 X = 1'b1; Y = 1'b0; CINtest = 1;
      	#10 X = 1'b1; Y = 1'b1; CINtest = 0;
        #10 X = 1'b1; Y = 1'b1; CINtest = 1;
      	#40 $finish;
    end

    always @(posedge clk) begin
    	$display("Time = %0t \tX = %b \tY = %b \tCIN = %b \tSUM = %b \tCOUT = %b", $time,X,Y,CINtest,SUMtest,COUTtest);
    end
  	initial begin
      	$dumpfile("tb_FULLADD_1.vcd"); 	// Extract waveforms from test bench to file.
      	$dumpvars(0, tb_FULLADD_1);		// Extract Variable values to file.
  	end
endmodule

EDAPlayground/Full-Adder1/Files/tb_FULLADD_1.vcd
$date
	Wed Mar 20 11:56:08 2024
$end

$version
	Synopsys VCS version S-2021.09
$end

$timescale
	1ns
$end

$comment Csum: 1 c78046a39f0fcee9 $end


$scope module tb_FULLADD_1 $end
$var reg 1 ! clk $end
$var reg 1 " X $end
$var reg 1 # Y $end
$var reg 1 $ CINtest $end
$var wire 1 % COUTtest $end
$var wire 1 & SUMtest $end

$scope module fa1 $end
$var wire 1 " A $end
$var wire 1 # B $end
$var wire 1 $ CIN $end
$var wire 1 & SUM $end
$var wire 1 % COUT $end
$upscope $end

$upscope $end

$enddefinitions $end

#0
$dumpvars
0$
0%
0&
0"
0#
0!
$end
#5
1!
#10
0!
#15
1!
#20
1$
0!
1&
#25
1!
#30
1#
0$
0!
#35
1!
#40
1$
0!
1%
0&
#45
1!
#50
1"
0#
0$
0!
0%
1&
#55
1!
#60
1$
0!
1%
0&
#65
1!
#70
1#
0$
0!
1%
#75
1!
#80
1$
0!
1&
