EDAPlayground/Practice1/Files/design.sv
// Code your design here

module practice1 (
  input a, b, c,
  output q
);
  
  wire aNandB, aNorB;
  
  assign aNandB = !(a & b);	// Intermediate connections
  assign aNorB = !(a | b);
  
  assign q = aNandB & aNorB & c;
  
endmodule

EDAPlayground/Practice1/Files/tb_practice1.sv
// Code your testbench here

module tb_practice1;

  // Clock Generation
  localparam CLK_PER = 10; // Clock period in units
  reg clk = 0;
  
  reg A, B, C;
  wire Q;

  // Instantiate the module under test
  practice1 p1 (
    .a(A),
    .b(B),
    .c(C),
    .q(Q)
  );

  always #((CLK_PER) / 2) clk = ~clk;

  initial begin

    A = 0; B = 0; C = 0; //Q = 0;	    // Initialize inputs

    #20 A = 0; B = 0; C = 0;
    #20 A = 0; B = 0; C = 1;
    #20 A = 0; B = 1; C = 0;
    #20 A = 0; B = 1; C = 1;
    #20 A = 1; B = 0; C = 0;
    #20 A = 1; B = 0; C = 1;
    #20 A = 1; B = 1; C = 0;
    #20 A = 1; B = 1; C = 1;
    #90 $finish;

  end

  always @(posedge clk) begin
    
    $display("Time = %0t \tA = %b \tB = %b \tC = %b \tQ = %b", $time, A, B, C, Q);

  end
  initial begin
    $dumpfile("tb_practice1.vcd"); 	// Extract waveforms from test bench to file.
    $dumpvars(0, tb_practice1);		// Extract Variable values to file.
  end

endmodule

EDAPlayground/Practice1/Files/tb_practice1.vcd
$date
	Wed Mar 13 14:32:37 2024
$end

$version
	Synopsys VCS version S-2021.09
$end

$timescale
	1ns
$end

$comment Csum: 1 09e563aeb89d468a $end


$scope module tb_practice1 $end
$var reg 1 ! clk $end
$var reg 1 " A $end
$var reg 1 # B $end
$var reg 1 $ C $end
$var wire 1 % Q $end

$scope module p1 $end
$var wire 1 " a $end
$var wire 1 # b $end
$var wire 1 $ c $end
$var wire 1 % q $end
$var wire 1 & aNandB $end
$var wire 1 ' aNorB $end
$upscope $end

$upscope $end

$enddefinitions $end

#0
$dumpvars
0"
0#
0$
0%
0!
x&
x'
$end
1&
1'
#5
1!
#10
0!
#15
1!
#20
0!
#25
1!
#30
0!
#35
1!
#40
1$
0!
1%
#45
1!
#50
0!
#55
1!
#60
1#
0'
0$
0!
0%
#65
1!
#70
0!
#75
1!
#80
1$
0!
#85
1!
#90
0!
#95
1!
#100
1"
0#
0$
0!
#105
1!
#110
0!
#115
1!
#120
1$
0!
#125
1!
#130
0!
#135
1!
#140
1#
0&
0$
0!
#145
1!
#150
0!
#155
1!
#160
1$
0!
